wdotool/__init__.py
wdotool/__version__.py
wdotool/wdotool_linux.py
python_wdotool-2024.9.6.dist-info/METADATA
python_wdotool-2024.9.6.dist-info/WHEEL
python_wdotool-2024.9.6.dist-info/licenses/LICENSE
python_wdotool-2024.9.6.dist-info/RECORD
